{
  "$schema": "https://mintlify.com/docs.json",
  "theme": "mint",
  "name": "RepoCloud Documentation",
  "colors": {
    "primary": "#0A82CC",
    "light": "#3DB0FF",
    "dark": "#0665A3"
  },
  "favicon": "/favicon.svg",
  "navigation": {
    "tabs": [
      {
        "tab": "Getting Started",
        "url": "introduction",
        "groups": [
          {
            "group": "Introduction",
            "pages": [
              "introduction",
              "quickstart"
            ]
          },
          {
            "group": "Platform Overview",
            "pages": [
              "platform/how-it-works",
              "platform/technical-details",
              "platform/supported-apps"
            ]
          }
        ]
      },
      {
        "tab": "User Guide",
        "url": "user-guide/deployment-basics",
        "groups": [
          {
            "group": "Deployments",
            "pages": [
              "user-guide/deployment-basics",
              "user-guide/one-click-deployment",
              "user-guide/managing-instances",
              "user-guide/custom-domains"
            ]
          },
          {
            "group": "Instance Management",
            "pages": [
              "user-guide/scaling",
              "user-guide/updates",
              "user-guide/environment-variables",
              "user-guide/troubleshooting"
            ]
          }
        ]
      },
      {
        "tab": "Platform Apps",
        "url": "platforms/introduction",
        "groups": [
          {
            "group": "Advanced Control",
            "pages": [
              "platforms/introduction",
              "platforms/coolify",
              "platforms/dokploy"
            ]
          }
        ]
      },
      {
        "tab": "Pricing & Billing",
        "url": "pricing/overview",
        "groups": [
          {
            "group": "Pricing",
            "pages": [
              "pricing/overview",
              "pricing/tiers",
              "pricing/comparison"
            ]
          },
          {
            "group": "Billing",
            "pages": [
              "pricing/autoscaling",
              "pricing/additional-resources"
            ]
          }
        ]
      },
      {
        "tab": "Resources",
        "url": "resources/affiliate-program",
        "groups": [
          {
            "group": "Programs",
            "pages": [
              "resources/affiliate-program",
              "resources/submit-app"
            ]
          },
          {
            "group": "Partner Resources",
            "pages": [
              "resources/partner-faq",
              "resources/app-documentation-guidelines",
              "resources/api-reference",
              "resources/partner-marketing"
            ]
          },
          {
            "group": "Legal",
            "pages": [
              "resources/privacy-policy",
              "resources/terms-conditions"
            ]
          }
        ]
      }
    ],
    "global": {
      "anchors": [
        {
          "anchor": "RepoCloud Home",
          "href": "https://repocloud.io",
          "icon": "house"
        },
        {
          "anchor": "Marketplace",
          "href": "https://repocloud.io/marketplace",
          "icon": "store"
        },
        {
          "anchor": "Blog",
          "href": "https://repocloud.io/blog",
          "icon": "newspaper"
        }
      ]
    }
  },
  "logo": {
    "light": "/logo/light.svg",
    "dark": "/logo/dark.svg"
  },
  "navbar": {
    "links": [
      {
        "label": "Support",
        "href": "mailto:team@repocloud.io"
      }
    ],
    "primary": {
      "type": "button",
      "label": "Dashboard",
      "href": "https://repocloud.io/dashboard"
    }
  },
  "footer": {
    "socials": {
      "twitter": "https://twitter.com/repocloudio",
      "github": "https://github.com/repocloud",
      "linkedin": "https://linkedin.com/company/repocloud"
    }
  }
}